MANIFEST.in
README.rst
README.txt
setup.cfg
setup.py
docs/CREDITS.txt
docs/HISTORY.txt
docs/INSTALL.txt
docs/LICENSE.GPL
docs/LICENSE.txt
src/sc/__init__.py
src/sc.base.uploader.egg-info/PKG-INFO
src/sc.base.uploader.egg-info/SOURCES.txt
src/sc.base.uploader.egg-info/dependency_links.txt
src/sc.base.uploader.egg-info/entry_points.txt
src/sc.base.uploader.egg-info/namespace_packages.txt
src/sc.base.uploader.egg-info/not-zip-safe
src/sc.base.uploader.egg-info/requires.txt
src/sc.base.uploader.egg-info/top_level.txt
src/sc/base/__init__.py
src/sc/base/uploader/README.txt
src/sc/base/uploader/__init__.py
src/sc/base/uploader/config.py
src/sc/base/uploader/configure.zcml
src/sc/base/uploader/overrides.zcml
src/sc/base/uploader/patch.py
src/sc/base/uploader/quickinstaller.py
src/sc/base/uploader/testing.py
src/sc/base/uploader/utility.py
src/sc/base/uploader/version.txt
src/sc/base/uploader/browser/__init__.py
src/sc/base/uploader/browser/configure.zcml
src/sc/base/uploader/browser/controlpanel.py
src/sc/base/uploader/browser/export.py
src/sc/base/uploader/browser/import.py
src/sc/base/uploader/browser/interfaces.py
src/sc/base/uploader/browser/menu.py
src/sc/base/uploader/browser/multiple-files.png
src/sc/base/uploader/browser/uploader.css
src/sc/base/uploader/browser/templates/import.pt
src/sc/base/uploader/locales/manual.pot
src/sc/base/uploader/locales/rebuildAll.sh
src/sc/base/uploader/locales/sc.base.uploader.pot
src/sc/base/uploader/locales/pt_BR/LC_MESSAGES/sc.base.uploader.mo
src/sc/base/uploader/locales/pt_BR/LC_MESSAGES/sc.base.uploader.po
src/sc/base/uploader/profiles/default/browserlayer.xml
src/sc/base/uploader/profiles/default/controlpanel.xml
src/sc/base/uploader/profiles/default/cssregistry.xml
src/sc/base/uploader/profiles/default/import_steps.xml
src/sc/base/uploader/profiles/default/metadata.xml
src/sc/base/uploader/profiles/default/propertiestool.xml
src/sc/base/uploader/profiles/default/sc.base.uploader.txt
src/sc/base/uploader/profiles/uninstall/sc.base.uploader.txt
src/sc/base/uploader/tests/__init__.py
src/sc/base/uploader/tests/foobar.zip
src/sc/base/uploader/tests/test_controlpanel.py
src/sc/base/uploader/tests/test_export.py
src/sc/base/uploader/tests/test_image.jpg
src/sc/base/uploader/tests/test_image.png
src/sc/base/uploader/tests/test_import.py
src/sc/base/uploader/tests/test_setup.py
