Metadata-Version: 1.1
Name: sc.base.uploader
Version: 1.0b3
Summary: A Plone package providing multiple-files upload
Home-page: https://github.com/simplesconsultoria/sc.base.uploader
Author: Simples Consultoria
Author-email: products@simplesconsultoria.com.br
License: GPL
Keywords: upload massuploader zip plone
Platform: UNKNOWN
Classifier: Development Status :: 3 - Alpha
Classifier: Environment :: Web Environment
Classifier: Framework :: Plone
Classifier: Framework :: Plone :: 4.2
Classifier: Intended Audience :: Developers
Classifier: Operating System :: OS Independent
Classifier: Programming Language :: Python
Classifier: Programming Language :: Python :: 2.7
Classifier: Topic :: Internet :: WWW/HTTP
Classifier: Topic :: Internet :: WWW/HTTP :: Dynamic Content
Classifier: Topic :: Software Development :: Libraries :: Python Modules
